splicejac/__init__.py
splicejac/pl.py
splicejac/tl.py
splicejac/plot/__init__.py
splicejac/plot/gene_variation.py
splicejac/plot/grn_comparison.py
splicejac/plot/grn_plots.py
splicejac/plot/instability.py
splicejac/plot/jacobian_visual.py
splicejac/plot/plotting_util.py
splicejac/plot/sankey_plots.py
splicejac/plot/sensitivity.py
splicejac/plot/signaling.py
splicejac/plot/umap_scatter.py
splicejac/tools/__init__.py
splicejac/tools/aux_functions.py
splicejac/tools/estimate_jacobian.py
splicejac/tools/export_methods.py
splicejac/tools/grn_comparison.py
splicejac/tools/grn_statistics.py
splicejac/tools/regr_method_sens.py
splicejac/tools/subsampling_sens.py
splicejac/tools/transitions.py
splicejac-0.0.1.dist-info/LICENSE
splicejac-0.0.1.dist-info/METADATA
splicejac-0.0.1.dist-info/WHEEL
splicejac-0.0.1.dist-info/top_level.txt
splicejac-0.0.1.dist-info/RECORD
