Metadata-Version: 2.1
Name: splicejac
Version: 0.0.1
Summary: spliceJAC is a python-based toolkit to reconstruct cell state-specific gene regulatory networks (GRN) and predict transition driver genes leading to cell differentiation
Home-page: https://github.com/federicobocci/spliceJAC
Author: Federico Bocci
Author-email: Federico Bocci <fbocci@uci.edu>
Classifier: Programming Language :: Python :: 3
Classifier: License :: OSI Approved :: MIT License
Classifier: Operating System :: OS Independent
Requires-Python: >=3.8
License-File: LICENSE
Provides-Extra: doc
Requires-Dist: sphinx (~=4.2.0) ; extra == 'doc'
Requires-Dist: myst-parser ; extra == 'doc'
Requires-Dist: sphinx-rtd-theme ; extra == 'doc'
